[
  {
    "buyTicketsUrl": null,
    "id": 1,
    "serie": 1188,
    "season": 2024,
    "homeTeamName": "Lukko",
    "awayTeamName": "HPK",
    "homeTeamId": "624554857:lukko",
    "awayTeamId": "55786244:hpk",
    "homeTeamPlaceholder": null,
    "awayTeamPlaceholder": null,
    "homeTeamGoals": 1,
    "awayTeamGoals": 2,
    "expectedHomeTeamGoals": 2.64,
    "expectedAwayTeamGoals": 3.17,
    "gameTime": 3600,
    "started": true,
    "ended": true,
    "homeTeamWinner": false,
    "spectators": 3011,
    "homeTeamRanking": null,
    "awayTeamRanking": null,
    "playOffPair": null,
    "playOffPhase": null,
    "playOffReqWins": null,
    "start": "2023-09-12T15:30:00Z",
    "finishedType": "ENDED_DURING_REGULAR_GAME_TIME",
    "iceRink": {
      "id": 166,
      "name": "Rauman jäähalli / Äijänsuo Areena",
      "latitude": 61.1203,
      "longitude": 21.501,
      "streetAddress": "Nortamonkatu 23",
      "zip": "26100",
      "city": "RAUMA"
    }
  },
  {
    "buyTicketsUrl": null,
    "id": 2,
    "serie": 1188,
    "season": 2024,
    "homeTeamName": "Jukurit",
    "awayTeamName": "KooKoo",
    "homeTeamId": "292293444:jukurit",
    "awayTeamId": "461765763:kookoo",
    "homeTeamPlaceholder": null,
    "awayTeamPlaceholder": null,
    "homeTeamGoals": 4,
    "awayTeamGoals": 1,
    "expectedHomeTeamGoals": 4.34,
    "expectedAwayTeamGoals": 1.92,
    "gameTime": 3600,
    "started": true,
    "ended": true,
    "homeTeamWinner": true,
    "spectators": 2280,
    "homeTeamRanking": null,
    "awayTeamRanking": null,
    "playOffPair": null,
    "playOffPhase": null,
    "playOffReqWins": null,
    "start": "2023-09-13T15:30:00Z",
    "finishedType": "ENDED_DURING_REGULAR_GAME_TIME",
    "iceRink": {
      "id": 111,
      "name": "Mikkelin jäähalli",
      "latitude": 61.6926,
      "longitude": 27.2546,
      "streetAddress": "Raviradantie 1",
      "zip": "50100",
      "city": "MIKKELI"
    }
  },
  {
    "buyTicketsUrl": null,
    "id": 3,
    "serie": 1188,
    "season": 2024,
    "homeTeamName": "JYP",
    "awayTeamName": "TPS",
    "homeTeamId": "219244634:jyp",
    "awayTeamId": "651304385:tps",
    "homeTeamPlaceholder": null,
    "awayTeamPlaceholder": null,
    "homeTeamGoals": 2,
    "awayTeamGoals": 3,
    "expectedHomeTeamGoals": 1.34,
    "expectedAwayTeamGoals": 2.05,
    "gameTime": 3688,
    "started": true,
    "ended": true,
    "homeTeamWinner": false,
    "spectators": 3066,
    "homeTeamRanking": null,
    "awayTeamRanking": null,
    "playOffPair": null,
    "playOffPhase": null,
    "playOffReqWins": null,
    "start": "2023-09-13T15:30:00Z",
    "finishedType": "ENDED_DURING_EXTENDED_GAME_TIME",
    "iceRink": {
      "id": 39,
      "name": "Jyväskylän jäähalli",
      "latitude": 62.2381,
      "longitude": 25.722,
      "streetAddress": "Rautpohjankatu 10",
      "zip": "40700",
      "city": "JYVÄSKYLÄ"
    }
  }
]